mi_module_zoo/__init__.py
mi_module_zoo/__version__.py
mi_module_zoo/mlp.py
mi_module_zoo/relationalmultiheadattention.py
mi_module_zoo/relationaltransformerlayers.py
mi_module_zoo/settransformer.py
mi_module_zoo/utils/__init__.py
mi_module_zoo/utils/activation.py
mi_module_zoo/utils/random.py
mi_module_zoo/utils/testing.py
tests/__init__.py
tests/test_activations.py
tests/test_mlp.py
tests/test_relationalmultiheadattention.py
tests/test_relationaltransformers.py
tests/test_settransformers.py
mi_module_zoo-1.0.0.dist-info/LICENSE
mi_module_zoo-1.0.0.dist-info/METADATA
mi_module_zoo-1.0.0.dist-info/WHEEL
mi_module_zoo-1.0.0.dist-info/top_level.txt
mi_module_zoo-1.0.0.dist-info/RECORD
