Metadata-Version: 2.1
Name: mi-module-zoo
Version: 1.0.0
Summary: Reusable PyTorch Modules
Home-page: https://github.com/microsoft/mi-module-zoo/
Author: Machine Intelligence
License: MIT
Project-URL: Bug Tracker, https://github.com/microsoft/mi-module-zoo/issues
Project-URL: Source Code, https://github.com/microsoft/mi-module-zoo
Platform: UNKNOWN
Classifier: License :: OSI Approved :: MIT License
Classifier: Topic :: Software Development :: Libraries
Classifier: Typing :: Typed
Classifier: Programming Language :: Python :: 3.7
Classifier: Programming Language :: Python :: 3.8
Classifier: Programming Language :: Python :: 3.9
Requires-Python: >=3.6.1
License-File: LICENSE
Requires-Dist: torch (>=1.9.1)
Requires-Dist: typing-extensions
Provides-Extra: aml
Requires-Dist: azureml ; extra == 'aml'
Provides-Extra: dev
Requires-Dist: black ; extra == 'dev'
Requires-Dist: isort ; extra == 'dev'
Requires-Dist: pre-commit ; extra == 'dev'
Requires-Dist: numpy ; extra == 'dev'
